cptd-2.1.4.dist-info/licenses/LICENSE
cptd_tools/__init__.py
cptd_tools/cptd_manifest.cptd
cptd_tools/create_command.md
cptd_tools/instruction.md
cptd_tools/main.py
cptd_tools/os_guard.py
cptd_tools/paths.py
cptd_tools/settings.json
cptd_tools/syntax_utils.py
cptd_tools/commands/__init__.py
cptd_tools/commands/__pycache__/__init__.cpython-313.pyc
cptd_tools/commands/__pycache__/command.cpython-313.pyc
cptd_tools/commands/about/about.py
cptd_tools/commands/about/manifest.json
cptd_tools/commands/about/manifest.yaml
cptd_tools/commands/command/command.py
cptd_tools/commands/command/manifest.json
cptd_tools/commands/command/manifest.yaml
cptd_tools/commands/cpdsl/main.py
cptd_tools/commands/cpdsl/manifest.json
cptd_tools/commands/cpdsl/manifest.yaml
cptd_tools/commands/cpdsl/__pycache__/main.cpython-313.pyc
cptd_tools/commands/dsl/dsl.py
cptd_tools/commands/dsl/manifest.json
cptd_tools/commands/dsl/manifest.yaml
cptd_tools/commands/gitauto/main.py
cptd_tools/commands/gitauto/manifest.json
cptd_tools/commands/gitauto/manifest.yaml
cptd_tools/commands/gitauto/util/__init__.py
cptd_tools/commands/gitauto/util/runner.py
cptd_tools/commands/gitauto/workflow/deploy.yaml
cptd_tools/commands/history/main.py
cptd_tools/commands/history/manifest.json
cptd_tools/commands/history/manifest.yaml
cptd_tools/commands/install/main.py
cptd_tools/commands/install/manifest.json
cptd_tools/commands/install/manifest.yaml
cptd_tools/commands/newcommand/manifest.json
cptd_tools/commands/newcommand/manifest.yaml
cptd_tools/commands/newcommand/newcommand.py
cptd_tools/commands/runner/main.py
cptd_tools/commands/runner/manifest.json
cptd_tools/commands/runner/manifest.yaml
cptd_tools/commands/runner/util/__init__.py
cptd_tools/commands/runner/util/runner.py
cptd_tools/commands/runner/workflow/deploy.yaml
cptd-2.1.4.dist-info/METADATA
cptd-2.1.4.dist-info/WHEEL
cptd-2.1.4.dist-info/entry_points.txt
cptd-2.1.4.dist-info/top_level.txt
cptd-2.1.4.dist-info/RECORD
